cruet/__init__.py
cruet/response/__init__.py
cruet/response/error.py
cruet/response/response.py
cruet/validation/__init__.py
cruet/validation/dataschema.py
cruet/validation/parser.py
cruet-0.0.3.dist-info/LICENSE
cruet-0.0.3.dist-info/METADATA
cruet-0.0.3.dist-info/WHEEL
cruet-0.0.3.dist-info/top_level.txt
cruet-0.0.3.dist-info/RECORD
