Metadata-Version: 2.1
Name: cruet
Version: 0.0.3
Summary: A simple toolkit for building microservices with flask
Home-page: https://github.com/AustralianSynchrotron/cruet
Author: Scientific Computing - Australian Synchrotron
Author-email: ascomputing@ansto.gov.au
License: BSD
Platform: UNKNOWN
Classifier: Development Status :: 2 - Pre-Alpha
Classifier: Environment :: Web Environment
Classifier: License :: OSI Approved :: BSD License
Classifier: Operating System :: OS Independent
Classifier: Programming Language :: Python :: 3
Classifier: Programming Language :: Python :: 3.7
Requires-Dist: Flask (>=1.1.1)
Requires-Dist: marshmallow (>=3.0.3)
Requires-Dist: webargs (>=5.4.0)
Requires-Dist: apispec (>=2.0.2)
Requires-Dist: PyYAML (>=5.1.2)
